[
  {
    "id": 1,
    "name": "Shirt for women",
    "price": "$19.99",
    "image": "/pictures/product8.jpg"
  },
  {
    "id": 2,
    "name": "Jeans",
    "price": "$9.99",
    "image": "/pictures/product2.jpg"
  },
  {
    "id": 3,
    "name": "Pants for women",
    "price": "$9.99",
    "image": "/pictures/product3.jpg"
  },
  {
    "id": 4,
    "name": "Pants for men",
    "price": "$29.99",
    "image": "/pictures/product4.jpg"
  },
  {
    "id": 5,
    "name": "Summer hat",
    "price": "$19.99",
    "image": "/pictures/product5.jpg"
  },
  {
    "id": 6,
    "name": "Dress for women",
    "price": "$6.99",
    "image": "/pictures/product6.jpg"
  },
  {
    "id": 7,
    "name": "Mens T-shirt",
    "price": "$9.99",
    "image": "/pictures/product7.jpg"
  },
  {
    "id": 8,
    "name": "Jeans",
    "price": "$29.99",
    "image": "/pictures/product8.jpg"
  },
  {
    "id": 17,
    "name": "Summer shirt for women",
    "price": "$24.99",
    "image": "/pictures/product16.jpg"
  },
  {
    "id": 9,
    "name": "Sea style dress",
    "price": "$19.99",
    "image": "/pictures/product9.jpg"
  },
  {
    "id": 10,
    "name": "Summer dress",
    "price": "$24.99",
    "image": "/pictures/product10.jpg"
  },
  {
    "id": 11,
    "name": "Summer dress",
    "price": "$24.99",
    "image": "/pictures/product11.jpg"
  },
  {
    "id": 12,
    "name": "Summer dress",
    "price": "$24.99",
    "image": "/pictures/product12.jpg"
  },
  {
    "id": 13,
    "name": "Summer shorts",
    "price": "$4.99",
    "image": "/pictures/product13.jpg"
  },
  {
    "id": 14,
    "name": "Summer dress",
    "price": "$24.99",
    "image": "/pictures/product14.jpg"
  },
  {
    "id": 15,
    "name": "Summer dress",
    "price": "$19.99",
    "image": "/pictures/product15.jpg"
  },
  {
    "id": 16,
    "name": "Summer shorts",
    "price": "$14.99",
    "image": "/pictures/product16.jpg"
  },
  {
    "id": 18,
    "name": "Summer shirt",
    "price": "$14.99",
    "image": "/pictures/product17.jpg"
  },
  {
    "id": 19,
    "name": "Dress for kids",
    "price": "$14.99",
    "image": "/pictures/product19.jpg"
  },
  {
    "id": 20,
    "name": "Dress for kids",
    "price": "$14.99",
    "image": "/pictures/product20.jpg"
  },
  {
    "id": 21,
    "name": "Dress for kids",
    "price": "$14.99",
    "image": "/pictures/product21.jpg"
  },
  {
    "id": 22,
    "name": "Dress for kids",
    "price": "$14.99",
    "image": "/pictures/product22.jpg"
  },
  {
    "id": 23,
    "name": "Dress for kids",
    "price": "$14.99",
    "image": "/pictures/product23.jpg"
  },
  {
    "id": 24,
    "name": "Running set",
    "price": "$34.99",
    "image": "/pictures/product24.jpg"
  },
  {
    "id": 25,
    "name": "Running set",
    "price": "$34.99",
    "image": "/pictures/product25.jpg"
  },
  {
    "id": 26,
    "name": "Running set",
    "price": "$34.99",
    "image": "/pictures/product26.jpg"
  },
  {
    "id": 27,
    "name": "Sport longsleeve",
    "price": "$24.99",
    "image": "/pictures/product27.png"
  },
  {
    "id": 28,
    "name": "Jacket for men",
    "price": "$64.99",
    "image": "/pictures/product28.png"
  },
  {
    "id": 29,
    "name": "Joga set",
    "price": "$44.99",
    "image": "/pictures/product29.png"
  },
  {
    "id": 30,
    "name": "Hiking jacket",
    "price": "$134.99",
    "image": "/pictures/product30.png"
  },
  {
    "id": 31,
    "name": "Hiking set",
    "price": "$34.99",
    "image": "/pictures/product31.png"
  },
  {
    "id": 32,
    "name": "Hiking set",
    "price": "$34.99",
    "image": "/pictures/product32.png"
  },
  {
    "id": 33,
    "name": "Running set",
    "price": "$34.99",
    "image": "/pictures/product33.png"
  },
  {
    "id": 34,
    "name": "Baby dress",
    "price": "$34.99",
    "image": "/pictures/product34.png"
  },
  {
    "id": 35,
    "name": "Pajamas for kids",
    "price": "$24.99",
    "image": "/pictures/product35.png"
  },
  {
    "id": 36,
    "name": "Boys outdoor set",
    "price": "$34.99",
    "image": "/pictures/product36.png"
  },
  {
    "id": 37,
    "name": "Boys outdoor set",
    "price": "$54.99",
    "image": "/pictures/product37.png"
  },
  {
    "id": 38,
    "name": "Baby set",
    "price": "$34.99",
    "image": "/pictures/product38.png"
  },
  {
    "id": 39,
    "name": "Longslive shirt",
    "price": "$34.99",
    "image": "/pictures/product39.png"
  },
  {
    "id": 40,
    "name": "Baby set",
    "price": "$24.99",
    "image": "/pictures/product40.png"
  }
]
